observatoriofcca/__init__.py
observatoriofcca/sniimapp.py
observatoriofcca-0.1.17.dist-info/METADATA
observatoriofcca-0.1.17.dist-info/WHEEL
observatoriofcca-0.1.17.dist-info/top_level.txt
observatoriofcca-0.1.17.dist-info/RECORD
