Metadata-Version: 2.1
Name: observatoriofcca
Version: 0.1.17
Summary: API - Observatorio de gestión pública e inteligencia de mercados
Home-page: https://sites.google.com/umich.mx/observatoriofcca
Author: Oscar de la Torre-Torres, Rodolfo López
Author-email: oscar.delatorre.torres@umich.mx
Maintainer: Felipe Andoni Luna Campos
Maintainer-email: fluna@umich.mx
License: UNKNOWN
Platform: UNKNOWN
Classifier: Programming Language :: Python :: 3
Classifier: License :: OSI Approved :: MIT License
Classifier: Operating System :: OS Independent
Requires-Dist: requests
